{
  "Breitengrad": "50.740157",
  "Bundesland": "Nordrhein-Westfalen",
  "E-Mail": "poststelle@eba.bund.de",
  "Hauptadresse": "Heinemannstraße 6",
  "Internetadresse": "https://www.eba.bund.de/DE/home_node.html",
  "Land": "DE",
  "Längengrad": "7.083861",
  "Organisation": "Eisenbahn-Bundesamt",
  "OrganisationDisplay": "EBA",
  "OrganisationId": 24446,
  "OrganisationKurz": "EBA",
  "Ort": "Bonn",
  "PLZ": 53175,
  "Ressort": "BMV",
  "Telefax": "+49 228 9826-9199",
  "Telefon": "+49 228 9826-0",
  "locations": [
    {
      "Breitengrad": "50.740157",
      "Bundesland": "Nordrhein-Westfalen",
      "E-Mail": "poststelle@eba.bund.de",
      "Hauptadresse": "Heinemannstraße 6",
      "Internetadresse": "https://www.eba.bund.de/DE/home_node.html",
      "Land": "DE",
      "Längengrad": "7.083861",
      "Organisation": "Eisenbahn-Bundesamt",
      "OrganisationDisplay": "EBA",
      "OrganisationId": 24446,
      "OrganisationKurz": "EBA",
      "Ort": "Bonn",
      "PLZ": 53175,
      "Ressort": "BMV",
      "Telefax": "+49 228 9826-9199",
      "Telefon": "+49 228 9826-0"
    }
  ]
}