{
  "Breitengrad": "54.3391185",
  "Bundesland": "Schleswig-Holstein",
  "E-Mail": "zbw@zbw-workspace.eu",
  "Hauptadresse": "D체sternbrooker Weg 120",
  "Internetadresse": "https://www.zbw.eu/de/",
  "Land": "DE",
  "L채ngengrad": "10.1555796",
  "Organisation": "ZBW - Leibniz Informationszentrum Wirtschaft",
  "OrganisationDisplay": "ZBW",
  "OrganisationId": 308346,
  "OrganisationKurz": "ZBW",
  "Ort": "Kiel",
  "PLZ": 24105,
  "Ressort": "BMFTR",
  "Telefon": "+49 431 8814-555",
  "Kategorie": "Leibniz-Institut",
  "Versteckt": true,
  "locations": [
    {
      "Breitengrad": "54.3391185",
      "Bundesland": "Schleswig-Holstein",
      "E-Mail": "zbw@zbw-workspace.eu",
      "Hauptadresse": "D체sternbrooker Weg 120",
      "Internetadresse": "https://www.zbw.eu/de/",
      "Land": "DE",
      "L채ngengrad": "10.1555796",
      "Organisation": "ZBW - Leibniz Informationszentrum Wirtschaft",
      "OrganisationDisplay": "ZBW",
      "OrganisationId": 308346,
      "OrganisationKurz": "ZBW",
      "Ort": "Kiel",
      "PLZ": 24105,
      "Ressort": "BMFTR",
      "Telefon": "+49 431 8814-555",
      "Kategorie": "Leibniz-Institut",
      "Versteckt": true
    }
  ]
}